odoo10_addon_base_fontawesome-10.0.4.7.0-py2.7-nspkg.pth
odoo/addons/base_fontawesome/README.rst
odoo/addons/base_fontawesome/__init__.py
odoo/addons/base_fontawesome/__manifest__.py
odoo/addons/base_fontawesome/static/description/icon.png
odoo/addons/base_fontawesome/static/lib/fontawesome-4.7.0/css/font-awesome.css
odoo/addons/base_fontawesome/static/lib/fontawesome-4.7.0/fonts/FontAwesome.otf
odoo/addons/base_fontawesome/static/lib/fontawesome-4.7.0/fonts/fontawesome-webfont.eot
odoo/addons/base_fontawesome/static/lib/fontawesome-4.7.0/fonts/fontawesome-webfont.svg
odoo/addons/base_fontawesome/static/lib/fontawesome-4.7.0/fonts/fontawesome-webfont.ttf
odoo/addons/base_fontawesome/static/lib/fontawesome-4.7.0/fonts/fontawesome-webfont.woff
odoo/addons/base_fontawesome/static/lib/fontawesome-4.7.0/fonts/fontawesome-webfont.woff2
odoo/addons/base_fontawesome/templates/assets.xml
odoo10_addon_base_fontawesome-10.0.4.7.0.dist-info/DESCRIPTION.rst
odoo10_addon_base_fontawesome-10.0.4.7.0.dist-info/METADATA
odoo10_addon_base_fontawesome-10.0.4.7.0.dist-info/RECORD
odoo10_addon_base_fontawesome-10.0.4.7.0.dist-info/WHEEL
odoo10_addon_base_fontawesome-10.0.4.7.0.dist-info/metadata.json
odoo10_addon_base_fontawesome-10.0.4.7.0.dist-info/namespace_packages.txt
odoo10_addon_base_fontawesome-10.0.4.7.0.dist-info/top_level.txt
